{
    "key": "HB 263",
    "session": "20231",
    "billPageUrl": "http://laws.leg.mt.gov/legprd/LAW0210W$BSIV.ActionQuery?P_BILL_NO1=263&P_BLTP_BILL_TYP_CD=HB&Z_ACTION=Find&P_SESS=20231",
    "billTextUrl": "http://leg.mt.gov/bills/2023/billhtml/HB0263.htm",
    "billPdfUrl": "http://leg.mt.gov/bills/2023/billpdf/HB0263.pdf",
    "lc": "LC0912",
    "title": "Revise insurance coverage for prescription eyedrop refills",
    "sponsor": "Amy Regier",
    "sponsorParty": "R",
    "sponsorDistrict": "HD 6",
    "statusDate": "04/19/2023",
    "lastAction": "Chapter Number Assigned",
    "billStatus": "Became Law",
    "fiscalNotesListUrl": null,
    "legalNoteUrl": null,
    "amendmentListUrl": null,
    "draftRequestor": null,
    "billRequestor": null,
    "primarySponsor": "Amy Regier",
    "subjects": [
        {
            "subject": "Health Care Services (see also: Health)",
            "fiscalCode": "",
            "voteReq": "Simple"
        },
        {
            "subject": "Insurance",
            "fiscalCode": "",
            "voteReq": "Simple"
        }
    ],
    "voteRequirements": [
        "Simple"
    ],
    "deadlineCategory": "General Bills",
    "transmittalDeadline": "03/03/2023",
    "amendedReturnDeadline": "04/18/2023"
}