[
    {
        "url": "http://leg.mt.gov/bills/2023/minutes/house/votesheets/HB0282JUH230126.pdf",
        "bill": "HB 282",
        "session": "20231",
        "action_id": "HB282-0025",
        "type": "committee",
        "seq_number": null,
        "error": null,
        "date": "January 26, 2023",
        "description": "Rep. Ler made a Motion that HB0282.001.001 Be Amended",
        "totals": {
            "Y": 11,
            "N": 8
        },
        "votes": [
            {
                "name": "Bishop, Laurie",
                "vote": "N"
            },
            {
                "name": "Carlson, Jennifer",
                "vote": "N"
            },
            {
                "name": "Deming, Lee",
                "vote": "Y"
            },
            {
                "name": "Duram, Neil",
                "vote": "Y"
            },
            {
                "name": "Etchart, Jodee",
                "vote": "Y"
            },
            {
                "name": "France, Tom",
                "vote": "N"
            },
            {
                "name": "Hawk, Donavon",
                "vote": "N"
            },
            {
                "name": "Hinkle, Caleb",
                "vote": "Y"
            },
            {
                "name": "Hinkle, Jedediah",
                "vote": "Y"
            },
            {
                "name": "Howell, SJ",
                "vote": "N"
            },
            {
                "name": "Kmetz, Greg",
                "vote": "Y"
            },
            {
                "name": "Knudsen, Casey",
                "vote": "Y"
            },
            {
                "name": "Ler, Brandon",
                "vote": "Y"
            },
            {
                "name": "Mitchell, Braxton",
                "vote": "Y"
            },
            {
                "name": "Regier, Amy",
                "vote": "Y"
            },
            {
                "name": "Rusk, Wayne",
                "vote": "N"
            },
            {
                "name": "Sheldon-Galloway, Lola",
                "vote": "Y"
            },
            {
                "name": "Smith, Laura",
                "vote": "N"
            },
            {
                "name": "Zephyr, Zooey",
                "vote": "N"
            }
        ]
    }
]