{
    "key": "HB 959",
    "session": "20231",
    "billPageUrl": "http://laws.leg.mt.gov/legprd/LAW0210W$BSIV.ActionQuery?P_BILL_NO1=959&P_BLTP_BILL_TYP_CD=HB&Z_ACTION=Find&P_SESS=20231",
    "billTextUrl": "http://leg.mt.gov/bills/2023/billhtml/HB0959.htm",
    "billPdfUrl": "http://leg.mt.gov/bills/2023/billpdf/HB0959.pdf",
    "lc": "LC3062",
    "title": "Allow regulation of roadside solicitation in unincorporated places",
    "sponsor": "Tanner Smith",
    "sponsorParty": "R",
    "sponsorDistrict": "HD 11",
    "statusDate": "03/28/2023",
    "lastAction": "(H) Referred to Committee -- (H) Local Government",
    "billStatus": "In First House Committee--Nontabled",
    "fiscalNotesListUrl": null,
    "legalNoteUrl": null,
    "amendmentListUrl": null,
    "draftRequestor": null,
    "billRequestor": null,
    "primarySponsor": "Tanner Smith",
    "subjects": [
        {
            "subject": "Appropriations  (see also: State Finance)",
            "fiscalCode": "Appropriation",
            "voteReq": "Simple"
        },
        {
            "subject": "Transportation  (see also: Motor Vehicles; Taxation--Transportation)",
            "fiscalCode": "",
            "voteReq": "Simple"
        }
    ],
    "voteRequirements": [
        "Simple"
    ],
    "deadlineCategory": "Appropriation Bills",
    "transmittalDeadline": "04/04/2023",
    "amendedReturnDeadline": "04/21/2023"
}