{
    "key": "HJ 28",
    "session": "20231",
    "billPageUrl": "http://laws.leg.mt.gov/legprd/LAW0210W$BSIV.ActionQuery?P_BILL_NO1=28&P_BLTP_BILL_TYP_CD=HJ&Z_ACTION=Find&P_SESS=20231",
    "billTextUrl": "http://leg.mt.gov/bills/2023/billhtml/HJ0028.htm",
    "billPdfUrl": "http://leg.mt.gov/bills/2023/billpdf/HJ0028.pdf",
    "lc": "LC1928",
    "title": "Interim study of continuum of long-term care services",
    "sponsor": "Michael Yakawich",
    "sponsorParty": "R",
    "sponsorDistrict": "HD 51",
    "statusDate": "04/27/2023",
    "lastAction": "(H) 2nd Reading Passed",
    "billStatus": "In First House--Through 2nd Reading",
    "fiscalNotesListUrl": null,
    "legalNoteUrl": null,
    "amendmentListUrl": null,
    "draftRequestor": null,
    "billRequestor": null,
    "primarySponsor": "Michael Yakawich",
    "subjects": [
        {
            "subject": "Health Care Services (see also: Health)",
            "fiscalCode": "",
            "voteReq": "Simple"
        },
        {
            "subject": "Legislature, Interim Studies",
            "fiscalCode": "",
            "voteReq": "Simple"
        },
        {
            "subject": "Senior Citizens  (see also: Retirement)",
            "fiscalCode": "",
            "voteReq": "Simple"
        },
        {
            "subject": "Social Services",
            "fiscalCode": "",
            "voteReq": "Simple"
        }
    ],
    "voteRequirements": [
        "Simple"
    ],
    "deadlineCategory": "Interim Study Resolutions",
    "transmittalDeadline": "04/28/2023",
    "amendedReturnDeadline": "05/05/2023"
}