[
    {
        "id": "SB558-0000",
        "bill": "SB 558",
        "session": "20231",
        "action": "(C) Draft Request Received",
        "actionUrl": null,
        "date": "12/20/2022",
        "hasVote": false,
        "committee": null,
        "recordings": []
    },
    {
        "id": "SB558-0001",
        "bill": "SB 558",
        "session": "20231",
        "action": "(C) Draft in Legal Review",
        "actionUrl": null,
        "date": "03/20/2023",
        "hasVote": false,
        "committee": null,
        "recordings": []
    },
    {
        "id": "SB558-0002",
        "bill": "SB 558",
        "session": "20231",
        "action": "(C) Draft in Edit",
        "actionUrl": null,
        "date": "03/21/2023",
        "hasVote": false,
        "committee": null,
        "recordings": []
    },
    {
        "id": "SB558-0003",
        "bill": "SB 558",
        "session": "20231",
        "action": "(C) Draft to Drafter - Edit Review",
        "actionUrl": null,
        "date": "03/23/2023",
        "hasVote": false,
        "committee": null,
        "recordings": []
    },
    {
        "id": "SB558-0004",
        "bill": "SB 558",
        "session": "20231",
        "action": "(C) Draft in Input/Proofing",
        "actionUrl": null,
        "date": "03/23/2023",
        "hasVote": false,
        "committee": null,
        "recordings": []
    },
    {
        "id": "SB558-0005",
        "bill": "SB 558",
        "session": "20231",
        "action": "(C) Draft in Final Drafter Review",
        "actionUrl": null,
        "date": "03/23/2023",
        "hasVote": false,
        "committee": null,
        "recordings": []
    },
    {
        "id": "SB558-0006",
        "bill": "SB 558",
        "session": "20231",
        "action": "(C) Bill Draft Text Available Electronically",
        "actionUrl": null,
        "date": "03/23/2023",
        "hasVote": false,
        "committee": null,
        "recordings": []
    },
    {
        "id": "SB558-0007",
        "bill": "SB 558",
        "session": "20231",
        "action": "(C) Executive Director Review",
        "actionUrl": null,
        "date": "03/23/2023",
        "hasVote": false,
        "committee": null,
        "recordings": []
    },
    {
        "id": "SB558-0008",
        "bill": "SB 558",
        "session": "20231",
        "action": "(C) Draft in Assembly",
        "actionUrl": null,
        "date": "03/24/2023",
        "hasVote": false,
        "committee": null,
        "recordings": []
    },
    {
        "id": "SB558-0009",
        "bill": "SB 558",
        "session": "20231",
        "action": "(C) Draft Ready for Delivery",
        "actionUrl": null,
        "date": "03/24/2023",
        "hasVote": false,
        "committee": null,
        "recordings": []
    },
    {
        "id": "SB558-0010",
        "bill": "SB 558",
        "session": "20231",
        "action": "(C) Executive Director Final Review",
        "actionUrl": null,
        "date": "03/24/2023",
        "hasVote": false,
        "committee": null,
        "recordings": []
    },
    {
        "id": "SB558-0011",
        "bill": "SB 558",
        "session": "20231",
        "action": "(C) Draft Ready for Delivery",
        "actionUrl": null,
        "date": "03/24/2023",
        "hasVote": false,
        "committee": null,
        "recordings": []
    },
    {
        "id": "SB558-0012",
        "bill": "SB 558",
        "session": "20231",
        "action": "(C) Draft Delivered to Requester",
        "actionUrl": null,
        "date": "03/27/2023",
        "hasVote": false,
        "committee": null,
        "recordings": []
    },
    {
        "id": "SB558-0013",
        "bill": "SB 558",
        "session": "20231",
        "action": "(S) Introduced",
        "actionUrl": null,
        "date": "03/27/2023",
        "hasVote": false,
        "committee": null,
        "recordings": []
    },
    {
        "id": "SB558-0014",
        "bill": "SB 558",
        "session": "20231",
        "action": "(C) Introduced Bill Text Available Electronically&nbsp&nbsp",
        "actionUrl": null,
        "date": "03/27/2023",
        "hasVote": false,
        "committee": null,
        "recordings": []
    },
    {
        "id": "SB558-0015",
        "bill": "SB 558",
        "session": "20231",
        "action": "(S) Referred to Committee",
        "actionUrl": null,
        "date": "03/27/2023",
        "hasVote": false,
        "committee": "(S) Local Government",
        "recordings": []
    },
    {
        "id": "SB558-0016",
        "bill": "SB 558",
        "session": "20231",
        "action": "(S) First Reading",
        "actionUrl": null,
        "date": "03/28/2023",
        "hasVote": false,
        "committee": null,
        "recordings": []
    },
    {
        "id": "SB558-0017",
        "bill": "SB 558",
        "session": "20231",
        "action": "(S) Hearing",
        "actionUrl": null,
        "date": "03/31/2023",
        "hasVote": false,
        "committee": "(S) Local Government",
        "recordings": []
    },
    {
        "id": "SB558-0018",
        "bill": "SB 558",
        "session": "20231",
        "action": "(S) Committee Executive Action--Bill Passed",
        "actionUrl": null,
        "date": "03/31/2023",
        "hasVote": true,
        "committee": "(S) Local Government",
        "recordings": []
    },
    {
        "id": "SB558-0019",
        "bill": "SB 558",
        "session": "20231",
        "action": "(S) Committee Report--Bill Passed",
        "actionUrl": null,
        "date": "04/03/2023",
        "hasVote": false,
        "committee": "(S) Local Government",
        "recordings": []
    },
    {
        "id": "SB558-0020",
        "bill": "SB 558",
        "session": "20231",
        "action": "(S) Scheduled for 2nd Reading",
        "actionUrl": null,
        "date": "04/03/2023",
        "hasVote": false,
        "committee": null,
        "recordings": []
    },
    {
        "id": "SB558-0021",
        "bill": "SB 558",
        "session": "20231",
        "action": "(S) 2nd Reading Passed",
        "actionUrl": null,
        "date": "04/03/2023",
        "hasVote": true,
        "committee": null,
        "recordings": []
    }
]