[
    {
        "id": "SB524-0000",
        "bill": "SB 524",
        "session": "20231",
        "action": "(C) Draft Request Received",
        "actionUrl": null,
        "date": "11/01/2022",
        "hasVote": false,
        "committee": null,
        "recordings": []
    },
    {
        "id": "SB524-0001",
        "bill": "SB 524",
        "session": "20231",
        "action": "(C) Draft On Hold",
        "actionUrl": null,
        "date": "11/09/2022",
        "hasVote": false,
        "committee": null,
        "recordings": []
    },
    {
        "id": "SB524-0002",
        "bill": "SB 524",
        "session": "20231",
        "action": "(C) Draft Taken Off Hold",
        "actionUrl": null,
        "date": "01/26/2023",
        "hasVote": false,
        "committee": null,
        "recordings": []
    },
    {
        "id": "SB524-0003",
        "bill": "SB 524",
        "session": "20231",
        "action": "(C) Draft in Legal Review",
        "actionUrl": null,
        "date": "03/15/2023",
        "hasVote": false,
        "committee": null,
        "recordings": []
    },
    {
        "id": "SB524-0004",
        "bill": "SB 524",
        "session": "20231",
        "action": "(C) Draft in Edit",
        "actionUrl": null,
        "date": "03/16/2023",
        "hasVote": false,
        "committee": null,
        "recordings": []
    },
    {
        "id": "SB524-0005",
        "bill": "SB 524",
        "session": "20231",
        "action": "(C) Draft to Drafter - Edit Review",
        "actionUrl": null,
        "date": "03/20/2023",
        "hasVote": false,
        "committee": null,
        "recordings": []
    },
    {
        "id": "SB524-0006",
        "bill": "SB 524",
        "session": "20231",
        "action": "(C) Draft in Input/Proofing",
        "actionUrl": null,
        "date": "03/20/2023",
        "hasVote": false,
        "committee": null,
        "recordings": []
    },
    {
        "id": "SB524-0007",
        "bill": "SB 524",
        "session": "20231",
        "action": "(C) Draft in Final Drafter Review",
        "actionUrl": null,
        "date": "03/20/2023",
        "hasVote": false,
        "committee": null,
        "recordings": []
    },
    {
        "id": "SB524-0008",
        "bill": "SB 524",
        "session": "20231",
        "action": "(C) Bill Draft Text Available Electronically",
        "actionUrl": null,
        "date": "03/20/2023",
        "hasVote": false,
        "committee": null,
        "recordings": []
    },
    {
        "id": "SB524-0009",
        "bill": "SB 524",
        "session": "20231",
        "action": "(C) Executive Director Review",
        "actionUrl": null,
        "date": "03/20/2023",
        "hasVote": false,
        "committee": null,
        "recordings": []
    },
    {
        "id": "SB524-0010",
        "bill": "SB 524",
        "session": "20231",
        "action": "(C) Draft in Assembly",
        "actionUrl": null,
        "date": "03/21/2023",
        "hasVote": false,
        "committee": null,
        "recordings": []
    },
    {
        "id": "SB524-0011",
        "bill": "SB 524",
        "session": "20231",
        "action": "(C) Draft Ready for Delivery",
        "actionUrl": null,
        "date": "03/21/2023",
        "hasVote": false,
        "committee": null,
        "recordings": []
    },
    {
        "id": "SB524-0012",
        "bill": "SB 524",
        "session": "20231",
        "action": "(C) Executive Director Final Review",
        "actionUrl": null,
        "date": "03/21/2023",
        "hasVote": false,
        "committee": null,
        "recordings": []
    },
    {
        "id": "SB524-0013",
        "bill": "SB 524",
        "session": "20231",
        "action": "(C) Draft Ready for Delivery",
        "actionUrl": null,
        "date": "03/21/2023",
        "hasVote": false,
        "committee": null,
        "recordings": []
    },
    {
        "id": "SB524-0014",
        "bill": "SB 524",
        "session": "20231",
        "action": "(C) Draft Delivered to Requester",
        "actionUrl": null,
        "date": "03/21/2023",
        "hasVote": false,
        "committee": null,
        "recordings": []
    },
    {
        "id": "SB524-0015",
        "bill": "SB 524",
        "session": "20231",
        "action": "(C) Fiscal Note Probable",
        "actionUrl": null,
        "date": "03/21/2023",
        "hasVote": false,
        "committee": null,
        "recordings": []
    },
    {
        "id": "SB524-0016",
        "bill": "SB 524",
        "session": "20231",
        "action": "(S) Introduced",
        "actionUrl": null,
        "date": "03/21/2023",
        "hasVote": false,
        "committee": null,
        "recordings": []
    },
    {
        "id": "SB524-0017",
        "bill": "SB 524",
        "session": "20231",
        "action": "(S) Fiscal Note Requested",
        "actionUrl": null,
        "date": "03/21/2023",
        "hasVote": false,
        "committee": null,
        "recordings": []
    },
    {
        "id": "SB524-0018",
        "bill": "SB 524",
        "session": "20231",
        "action": "(C) Introduced Bill Text Available Electronically&nbsp&nbsp",
        "actionUrl": null,
        "date": "03/21/2023",
        "hasVote": false,
        "committee": null,
        "recordings": []
    },
    {
        "id": "SB524-0019",
        "bill": "SB 524",
        "session": "20231",
        "action": "(S) Referred to Committee",
        "actionUrl": null,
        "date": "03/22/2023",
        "hasVote": false,
        "committee": "(S) Judiciary",
        "recordings": []
    },
    {
        "id": "SB524-0020",
        "bill": "SB 524",
        "session": "20231",
        "action": "(S) First Reading",
        "actionUrl": null,
        "date": "03/22/2023",
        "hasVote": false,
        "committee": null,
        "recordings": []
    },
    {
        "id": "SB524-0021",
        "bill": "SB 524",
        "session": "20231",
        "action": "(S) Fiscal Note Received",
        "actionUrl": null,
        "date": "03/27/2023",
        "hasVote": false,
        "committee": null,
        "recordings": []
    },
    {
        "id": "SB524-0022",
        "bill": "SB 524",
        "session": "20231",
        "action": "(C) Fiscal Note Unsigned",
        "actionUrl": null,
        "date": "03/27/2023",
        "hasVote": false,
        "committee": null,
        "recordings": []
    },
    {
        "id": "SB524-0023",
        "bill": "SB 524",
        "session": "20231",
        "action": "(S) Fiscal Note Printed",
        "actionUrl": null,
        "date": "03/27/2023",
        "hasVote": false,
        "committee": null,
        "recordings": []
    },
    {
        "id": "SB524-0024",
        "bill": "SB 524",
        "session": "20231",
        "action": "(S) Hearing",
        "actionUrl": null,
        "date": "03/28/2023",
        "hasVote": false,
        "committee": "(S) Judiciary",
        "recordings": [
            "http://sg001-harmony.sliq.net/00309/Harmony/en/PowerBrowser/PowerBrowserV2/20170221/-1/47983?agendaId=265979",
            "http://sg001-harmony.sliq.net/00309/Harmony/en/PowerBrowser/PowerBrowserV2/20170221/-1/49326?agendaId=268273"
        ]
    },
    {
        "id": "SB524-0025",
        "bill": "SB 524",
        "session": "20231",
        "action": "(C) Amendments Available",
        "actionUrl": null,
        "date": "03/28/2023",
        "hasVote": false,
        "committee": null,
        "recordings": []
    },
    {
        "id": "SB524-0026",
        "bill": "SB 524",
        "session": "20231",
        "action": "(S) Committee Executive Action--Bill Passed as Amended",
        "actionUrl": null,
        "date": "03/30/2023",
        "hasVote": true,
        "committee": "(S) Judiciary",
        "recordings": []
    },
    {
        "id": "SB524-0027",
        "bill": "SB 524",
        "session": "20231",
        "action": "(C) Printed - New Version Available&nbsp&nbsp",
        "actionUrl": null,
        "date": "03/31/2023",
        "hasVote": false,
        "committee": null,
        "recordings": []
    },
    {
        "id": "SB524-0028",
        "bill": "SB 524",
        "session": "20231",
        "action": "(S) Committee Report--Bill Passed as Amended",
        "actionUrl": null,
        "date": "03/31/2023",
        "hasVote": false,
        "committee": "(S) Judiciary",
        "recordings": []
    },
    {
        "id": "SB524-0029",
        "bill": "SB 524",
        "session": "20231",
        "action": "(S) Scheduled for 2nd Reading",
        "actionUrl": null,
        "date": "04/03/2023",
        "hasVote": false,
        "committee": null,
        "recordings": []
    },
    {
        "id": "SB524-0030",
        "bill": "SB 524",
        "session": "20231",
        "action": "(S) 2nd Reading Motion to Amend Failed",
        "actionUrl": null,
        "date": "04/03/2023",
        "hasVote": true,
        "committee": null,
        "recordings": []
    },
    {
        "id": "SB524-0031",
        "bill": "SB 524",
        "session": "20231",
        "action": "(S) 2nd Reading Passed",
        "actionUrl": null,
        "date": "04/03/2023",
        "hasVote": true,
        "committee": "  ",
        "recordings": [
            "http://sg001-harmony.sliq.net/00309/Harmony/en/PowerBrowser/PowerBrowserV2/20170221/-1/49430?agendaId=269231",
            "http://sg001-harmony.sliq.net/00309/Harmony/en/PowerBrowser/PowerBrowserV2/20170221/-1/46246?agendaId=268872"
        ]
    },
    {
        "id": "SB524-0032",
        "bill": "SB 524",
        "session": "20231",
        "action": "(S) Scheduled for 3rd Reading",
        "actionUrl": null,
        "date": "04/04/2023",
        "hasVote": false,
        "committee": null,
        "recordings": []
    },
    {
        "id": "SB524-0033",
        "bill": "SB 524",
        "session": "20231",
        "action": "(S) 3rd Reading Passed",
        "actionUrl": null,
        "date": "04/04/2023",
        "hasVote": true,
        "committee": null,
        "recordings": []
    },
    {
        "id": "SB524-0034",
        "bill": "SB 524",
        "session": "20231",
        "action": "(S) Transmitted to House",
        "actionUrl": null,
        "date": "04/04/2023",
        "hasVote": false,
        "committee": null,
        "recordings": []
    },
    {
        "id": "SB524-0035",
        "bill": "SB 524",
        "session": "20231",
        "action": "(H) Referred to Committee",
        "actionUrl": null,
        "date": "04/05/2023",
        "hasVote": false,
        "committee": "(H) Taxation",
        "recordings": []
    },
    {
        "id": "SB524-0036",
        "bill": "SB 524",
        "session": "20231",
        "action": "(H) First Reading",
        "actionUrl": null,
        "date": "04/05/2023",
        "hasVote": false,
        "committee": null,
        "recordings": []
    },
    {
        "id": "SB524-0037",
        "bill": "SB 524",
        "session": "20231",
        "action": "(H) Hearing",
        "actionUrl": null,
        "date": "04/13/2023",
        "hasVote": false,
        "committee": "(H) Taxation",
        "recordings": [
            "http://sg001-harmony.sliq.net/00309/Harmony/en/PowerBrowser/PowerBrowserV2/20170221/-1/47865?agendaId=272375",
            "http://sg001-harmony.sliq.net/00309/Harmony/en/PowerBrowser/PowerBrowserV2/20170221/-1/49548?agendaId=274057"
        ]
    },
    {
        "id": "SB524-0038",
        "bill": "SB 524",
        "session": "20231",
        "action": "(H) Tabled in Committee",
        "actionUrl": null,
        "date": "04/17/2023",
        "hasVote": true,
        "committee": "(H) Taxation",
        "recordings": []
    }
]