[
    {
        "id": "SJ19-0000",
        "bill": "SJ 19",
        "session": "20231",
        "action": "(C) Draft Request Received",
        "actionUrl": null,
        "date": "10/06/2022",
        "hasVote": false,
        "committee": null,
        "recordings": []
    },
    {
        "id": "SJ19-0001",
        "bill": "SJ 19",
        "session": "20231",
        "action": "(C) Draft On Hold",
        "actionUrl": null,
        "date": "01/12/2023",
        "hasVote": false,
        "committee": null,
        "recordings": []
    },
    {
        "id": "SJ19-0002",
        "bill": "SJ 19",
        "session": "20231",
        "action": "(C) Draft Taken Off Hold",
        "actionUrl": null,
        "date": "03/29/2023",
        "hasVote": false,
        "committee": null,
        "recordings": []
    },
    {
        "id": "SJ19-0003",
        "bill": "SJ 19",
        "session": "20231",
        "action": "(C) Draft to Requester for Review",
        "actionUrl": null,
        "date": "03/29/2023",
        "hasVote": false,
        "committee": null,
        "recordings": []
    },
    {
        "id": "SJ19-0004",
        "bill": "SJ 19",
        "session": "20231",
        "action": "(C) Draft in Legal Review",
        "actionUrl": null,
        "date": "03/29/2023",
        "hasVote": false,
        "committee": null,
        "recordings": []
    },
    {
        "id": "SJ19-0005",
        "bill": "SJ 19",
        "session": "20231",
        "action": "(C) Draft in Edit",
        "actionUrl": null,
        "date": "03/30/2023",
        "hasVote": false,
        "committee": null,
        "recordings": []
    },
    {
        "id": "SJ19-0006",
        "bill": "SJ 19",
        "session": "20231",
        "action": "(C) Draft to Drafter - Edit Review",
        "actionUrl": null,
        "date": "03/30/2023",
        "hasVote": false,
        "committee": null,
        "recordings": []
    },
    {
        "id": "SJ19-0007",
        "bill": "SJ 19",
        "session": "20231",
        "action": "(C) Draft in Input/Proofing",
        "actionUrl": null,
        "date": "03/30/2023",
        "hasVote": false,
        "committee": null,
        "recordings": []
    },
    {
        "id": "SJ19-0008",
        "bill": "SJ 19",
        "session": "20231",
        "action": "(C) Draft in Final Drafter Review",
        "actionUrl": null,
        "date": "03/30/2023",
        "hasVote": false,
        "committee": null,
        "recordings": []
    },
    {
        "id": "SJ19-0009",
        "bill": "SJ 19",
        "session": "20231",
        "action": "(C) Bill Draft Text Available Electronically",
        "actionUrl": null,
        "date": "03/30/2023",
        "hasVote": false,
        "committee": null,
        "recordings": []
    },
    {
        "id": "SJ19-0010",
        "bill": "SJ 19",
        "session": "20231",
        "action": "(C) Executive Director Review",
        "actionUrl": null,
        "date": "03/30/2023",
        "hasVote": false,
        "committee": null,
        "recordings": []
    },
    {
        "id": "SJ19-0011",
        "bill": "SJ 19",
        "session": "20231",
        "action": "(C) Draft in Assembly",
        "actionUrl": null,
        "date": "03/31/2023",
        "hasVote": false,
        "committee": null,
        "recordings": []
    },
    {
        "id": "SJ19-0012",
        "bill": "SJ 19",
        "session": "20231",
        "action": "(C) Draft Ready for Delivery",
        "actionUrl": null,
        "date": "03/31/2023",
        "hasVote": false,
        "committee": null,
        "recordings": []
    },
    {
        "id": "SJ19-0013",
        "bill": "SJ 19",
        "session": "20231",
        "action": "(C) Executive Director Final Review",
        "actionUrl": null,
        "date": "03/31/2023",
        "hasVote": false,
        "committee": null,
        "recordings": []
    },
    {
        "id": "SJ19-0014",
        "bill": "SJ 19",
        "session": "20231",
        "action": "(C) Draft Ready for Delivery",
        "actionUrl": null,
        "date": "04/03/2023",
        "hasVote": false,
        "committee": null,
        "recordings": []
    },
    {
        "id": "SJ19-0015",
        "bill": "SJ 19",
        "session": "20231",
        "action": "(C) Draft Delivered to Requester",
        "actionUrl": null,
        "date": "04/03/2023",
        "hasVote": false,
        "committee": null,
        "recordings": []
    },
    {
        "id": "SJ19-0016",
        "bill": "SJ 19",
        "session": "20231",
        "action": "(S) Introduced",
        "actionUrl": null,
        "date": "04/03/2023",
        "hasVote": false,
        "committee": null,
        "recordings": []
    },
    {
        "id": "SJ19-0017",
        "bill": "SJ 19",
        "session": "20231",
        "action": "(S) Referred to Committee",
        "actionUrl": null,
        "date": "04/03/2023",
        "hasVote": false,
        "committee": "(S) State Administration",
        "recordings": []
    },
    {
        "id": "SJ19-0018",
        "bill": "SJ 19",
        "session": "20231",
        "action": "(C) Introduced Bill Text Available Electronically&nbsp&nbsp",
        "actionUrl": null,
        "date": "04/04/2023",
        "hasVote": false,
        "committee": null,
        "recordings": []
    },
    {
        "id": "SJ19-0019",
        "bill": "SJ 19",
        "session": "20231",
        "action": "(S) First Reading",
        "actionUrl": null,
        "date": "04/04/2023",
        "hasVote": false,
        "committee": null,
        "recordings": []
    },
    {
        "id": "SJ19-0020",
        "bill": "SJ 19",
        "session": "20231",
        "action": "(S) Hearing Canceled",
        "actionUrl": null,
        "date": "04/14/2023",
        "hasVote": false,
        "committee": "(S) State Administration",
        "recordings": []
    },
    {
        "id": "SJ19-0021",
        "bill": "SJ 19",
        "session": "20231",
        "action": "(S) Hearing Canceled",
        "actionUrl": null,
        "date": "04/15/2023",
        "hasVote": false,
        "committee": "(S) State Administration",
        "recordings": []
    },
    {
        "id": "SJ19-0022",
        "bill": "SJ 19",
        "session": "20231",
        "action": "(S) Hearing",
        "actionUrl": null,
        "date": "04/17/2023",
        "hasVote": false,
        "committee": "(S) State Administration",
        "recordings": [
            "http://sg001-harmony.sliq.net/00309/Harmony/en/PowerBrowser/PowerBrowserV2/20170221/-1/46772?agendaId=273501",
            "http://sg001-harmony.sliq.net/00309/Harmony/en/PowerBrowser/PowerBrowserV2/20170221/-1/49609?agendaId=275223"
        ]
    },
    {
        "id": "SJ19-0023",
        "bill": "SJ 19",
        "session": "20231",
        "action": "(S) Committee Executive Action--Bill Passed",
        "actionUrl": null,
        "date": "04/17/2023",
        "hasVote": true,
        "committee": "(S) State Administration",
        "recordings": []
    },
    {
        "id": "SJ19-0024",
        "bill": "SJ 19",
        "session": "20231",
        "action": "(S) Committee Report--Bill Passed",
        "actionUrl": null,
        "date": "04/18/2023",
        "hasVote": false,
        "committee": "(S) State Administration",
        "recordings": []
    },
    {
        "id": "SJ19-0025",
        "bill": "SJ 19",
        "session": "20231",
        "action": "(S) Scheduled for 2nd Reading",
        "actionUrl": null,
        "date": "04/19/2023",
        "hasVote": false,
        "committee": null,
        "recordings": []
    },
    {
        "id": "SJ19-0026",
        "bill": "SJ 19",
        "session": "20231",
        "action": "(S) 2nd Reading Passed",
        "actionUrl": null,
        "date": "04/19/2023",
        "hasVote": true,
        "committee": "  ",
        "recordings": [
            "http://sg001-harmony.sliq.net/00309/Harmony/en/PowerBrowser/PowerBrowserV2/20170221/-1/49658?agendaId=275673",
            "http://sg001-harmony.sliq.net/00309/Harmony/en/PowerBrowser/PowerBrowserV2/20170221/-1/46258?agendaId=274869"
        ]
    },
    {
        "id": "SJ19-0027",
        "bill": "SJ 19",
        "session": "20231",
        "action": "(S) Scheduled for 3rd Reading",
        "actionUrl": null,
        "date": "04/20/2023",
        "hasVote": false,
        "committee": null,
        "recordings": []
    },
    {
        "id": "SJ19-0028",
        "bill": "SJ 19",
        "session": "20231",
        "action": "(S) 3rd Reading Passed",
        "actionUrl": null,
        "date": "04/20/2023",
        "hasVote": true,
        "committee": null,
        "recordings": []
    },
    {
        "id": "SJ19-0029",
        "bill": "SJ 19",
        "session": "20231",
        "action": "(S) Transmitted to House",
        "actionUrl": null,
        "date": "04/21/2023",
        "hasVote": false,
        "committee": null,
        "recordings": []
    },
    {
        "id": "SJ19-0030",
        "bill": "SJ 19",
        "session": "20231",
        "action": "(H) Referred to Committee",
        "actionUrl": null,
        "date": "04/26/2023",
        "hasVote": false,
        "committee": "(H) State Administration",
        "recordings": []
    },
    {
        "id": "SJ19-0031",
        "bill": "SJ 19",
        "session": "20231",
        "action": "(H) First Reading",
        "actionUrl": null,
        "date": "04/26/2023",
        "hasVote": false,
        "committee": null,
        "recordings": []
    },
    {
        "id": "SJ19-0032",
        "bill": "SJ 19",
        "session": "20231",
        "action": "(H) Hearing",
        "actionUrl": null,
        "date": "04/27/2023",
        "hasVote": false,
        "committee": "(H) State Administration",
        "recordings": []
    },
    {
        "id": "SJ19-0033",
        "bill": "SJ 19",
        "session": "20231",
        "action": "(H) Committee Executive Action--Bill Concurred",
        "actionUrl": null,
        "date": "04/27/2023",
        "hasVote": true,
        "committee": "(H) State Administration",
        "recordings": []
    },
    {
        "id": "SJ19-0034",
        "bill": "SJ 19",
        "session": "20231",
        "action": "(H) Committee Report--Bill Concurred",
        "actionUrl": null,
        "date": "04/27/2023",
        "hasVote": false,
        "committee": "(H) State Administration",
        "recordings": []
    },
    {
        "id": "SJ19-0035",
        "bill": "SJ 19",
        "session": "20231",
        "action": "(H) Scheduled for 2nd Reading",
        "actionUrl": null,
        "date": "04/28/2023",
        "hasVote": false,
        "committee": null,
        "recordings": []
    },
    {
        "id": "SJ19-0036",
        "bill": "SJ 19",
        "session": "20231",
        "action": "(H) 2nd Reading Concurred",
        "actionUrl": null,
        "date": "04/28/2023",
        "hasVote": true,
        "committee": null,
        "recordings": []
    }
]