[
    {
        "url": "http://leg.mt.gov/bills/2023/minutes/senate/votesheets/SJ0037ENS230427.pdf",
        "bill": "SJ 37",
        "session": "20231",
        "action_id": "SJ37-0018",
        "type": "committee",
        "seq_number": null,
        "error": null,
        "date": "April 27, 2023",
        "description": "Sen. Small made a Motion that SJ 37 Resolution Adopted",
        "totals": {
            "Y": 10,
            "N": 2
        },
        "votes": [
            {
                "name": "Small, Jason",
                "vote": "Y"
            },
            {
                "name": "Lynch, Ryan",
                "vote": "Y"
            },
            {
                "name": "Cuffe, Mike;byproxy",
                "vote": "Y"
            },
            {
                "name": "Ellis, Janet;byproxy",
                "vote": "Y"
            },
            {
                "name": "Fitzpatrick, Steve;byproxy",
                "vote": "N"
            },
            {
                "name": "Hayman, Denise;byproxy",
                "vote": "Y"
            },
            {
                "name": "Molnar, Brad",
                "vote": "Y"
            },
            {
                "name": "Pope, Christopher;byproxy",
                "vote": "Y"
            },
            {
                "name": "Regier, Keith",
                "vote": "N"
            },
            {
                "name": "Tempel, Russel(Russ)",
                "vote": "Y"
            },
            {
                "name": "Zolnikov, Daniel;byproxy",
                "vote": "Y"
            },
            {
                "name": "Sales, Walt",
                "vote": "Y"
            }
        ]
    },
    {
        "url": "http://laws.leg.mt.gov/legprd/LAW0211W$BLAC.VoteTabulation?P_VOTE_SEQ=S2723&P_SESS=20231",
        "bill": "SJ 37",
        "session": "20231",
        "action_id": "SJ37-0021",
        "type": "floor",
        "seq_number": "S2723",
        "date": "April 28, 2023",
        "description": "Do Pass",
        "totals": {
            "Y": 32,
            "N": 18,
            "E": 0,
            "A": 0
        },
        "votes": [
            {
                "name": "Bartel, Dan",
                "vote": "N"
            },
            {
                "name": "Flowers, Pat",
                "vote": "Y"
            },
            {
                "name": "Lynch, Ryan",
                "vote": "Y"
            },
            {
                "name": "Sales, Walt",
                "vote": "Y"
            },
            {
                "name": "Beard, Becky",
                "vote": "N"
            },
            {
                "name": "Fox, Mike",
                "vote": "Y"
            },
            {
                "name": "Mandeville, Forrest",
                "vote": "Y"
            },
            {
                "name": "Salomon, Daniel",
                "vote": "Y"
            },
            {
                "name": "Bogner, Kenneth",
                "vote": "Y"
            },
            {
                "name": "Friedel, Chris",
                "vote": "Y"
            },
            {
                "name": "Manzella, Theresa",
                "vote": "N"
            },
            {
                "name": "Small, Jason",
                "vote": "Y"
            },
            {
                "name": "Boldman, Ellie",
                "vote": "Y"
            },
            {
                "name": "Fuller, John",
                "vote": "N"
            },
            {
                "name": "McClafferty, Edith (Edie)",
                "vote": "Y"
            },
            {
                "name": "Tempel, Russel (Russ)",
                "vote": "N"
            },
            {
                "name": "Brown, Bob",
                "vote": "N"
            },
            {
                "name": "Gillespie, Bruce",
                "vote": "Y"
            },
            {
                "name": "McGillvray, Tom",
                "vote": "Y"
            },
            {
                "name": "Trebas, Jeremy",
                "vote": "N"
            },
            {
                "name": "Cuffe, Mike",
                "vote": "N"
            },
            {
                "name": "Glimm, Carl",
                "vote": "Y"
            },
            {
                "name": "McKamey, Wendy",
                "vote": "Y"
            },
            {
                "name": "Usher, Barry",
                "vote": "Y"
            },
            {
                "name": "Curdy, Willis",
                "vote": "Y"
            },
            {
                "name": "Gross, Jen",
                "vote": "Y"
            },
            {
                "name": "Molnar, Brad",
                "vote": "Y"
            },
            {
                "name": "Vance, Shelley",
                "vote": "N"
            },
            {
                "name": "Dunwell, Mary Ann",
                "vote": "Y"
            },
            {
                "name": "Hayman, Denise",
                "vote": "Y"
            },
            {
                "name": "Morigeau, Shane",
                "vote": "Y"
            },
            {
                "name": "Vermeire, Terry",
                "vote": "Y"
            },
            {
                "name": "Ellis, Janet",
                "vote": "Y"
            },
            {
                "name": "Hertz, Greg",
                "vote": "N"
            },
            {
                "name": "Noland, Mark",
                "vote": "N"
            },
            {
                "name": "Webber, Susan",
                "vote": "Y"
            },
            {
                "name": "Ellsworth, Jason",
                "vote": "N"
            },
            {
                "name": "Hinebauch, Steve",
                "vote": "N"
            },
            {
                "name": "O'Brien, Shannon",
                "vote": "Y"
            },
            {
                "name": "Welborn, Jeffrey",
                "vote": "Y"
            },
            {
                "name": "Emrich, Daniel",
                "vote": "Y"
            },
            {
                "name": "Kelker, Kathy",
                "vote": "N"
            },
            {
                "name": "Olsen, Andrea",
                "vote": "Y"
            },
            {
                "name": "Zolnikov, Daniel",
                "vote": "Y"
            },
            {
                "name": "Esp, John",
                "vote": "N"
            },
            {
                "name": "Lang, Mike",
                "vote": "Y"
            },
            {
                "name": "Pope, Christopher",
                "vote": "Y"
            },
            {
                "name": "Fitzpatrick, Steve",
                "vote": "N"
            },
            {
                "name": "Lenz, Dennis",
                "vote": "N"
            },
            {
                "name": "Regier, Keith",
                "vote": "N"
            }
        ]
    },
    {
        "url": "http://laws.leg.mt.gov/legprd/LAW0211W$BLAC.VoteTabulation?P_VOTE_SEQ=S2735&P_SESS=20231",
        "bill": "SJ 37",
        "session": "20231",
        "action_id": "SJ37-0022",
        "type": "floor",
        "seq_number": "S2735",
        "date": "April 28, 2023",
        "description": "Do Pass",
        "totals": {
            "Y": 32,
            "N": 16,
            "E": 2,
            "A": 0
        },
        "votes": [
            {
                "name": "Bartel, Dan",
                "vote": "N"
            },
            {
                "name": "Flowers, Pat",
                "vote": "Y"
            },
            {
                "name": "Lynch, Ryan",
                "vote": "Y"
            },
            {
                "name": "Sales, Walt",
                "vote": "Y"
            },
            {
                "name": "Beard, Becky",
                "vote": "N"
            },
            {
                "name": "Fox, Mike",
                "vote": "Y"
            },
            {
                "name": "Mandeville, Forrest",
                "vote": "Y"
            },
            {
                "name": "Salomon, Daniel",
                "vote": "Y"
            },
            {
                "name": "Bogner, Kenneth",
                "vote": "Y"
            },
            {
                "name": "Friedel, Chris",
                "vote": "Y"
            },
            {
                "name": "Manzella, Theresa",
                "vote": "Y"
            },
            {
                "name": "Small, Jason",
                "vote": "N"
            },
            {
                "name": "Boldman, Ellie",
                "vote": "Y"
            },
            {
                "name": "Fuller, John",
                "vote": "N"
            },
            {
                "name": "McClafferty, Edith (Edie)",
                "vote": "Y"
            },
            {
                "name": "Tempel, Russel (Russ)",
                "vote": "N"
            },
            {
                "name": "Brown, Bob",
                "vote": "N"
            },
            {
                "name": "Gillespie, Bruce",
                "vote": "Y"
            },
            {
                "name": "McGillvray, Tom",
                "vote": "Y"
            },
            {
                "name": "Trebas, Jeremy",
                "vote": "N"
            },
            {
                "name": "Cuffe, Mike",
                "vote": "E"
            },
            {
                "name": "Glimm, Carl",
                "vote": "N"
            },
            {
                "name": "McKamey, Wendy",
                "vote": "Y"
            },
            {
                "name": "Usher, Barry",
                "vote": "Y"
            },
            {
                "name": "Curdy, Willis",
                "vote": "Y"
            },
            {
                "name": "Gross, Jen",
                "vote": "E"
            },
            {
                "name": "Molnar, Brad",
                "vote": "Y"
            },
            {
                "name": "Vance, Shelley",
                "vote": "Y"
            },
            {
                "name": "Dunwell, Mary Ann",
                "vote": "Y"
            },
            {
                "name": "Hayman, Denise",
                "vote": "Y"
            },
            {
                "name": "Morigeau, Shane",
                "vote": "Y"
            },
            {
                "name": "Vermeire, Terry",
                "vote": "Y"
            },
            {
                "name": "Ellis, Janet",
                "vote": "Y"
            },
            {
                "name": "Hertz, Greg",
                "vote": "N"
            },
            {
                "name": "Noland, Mark",
                "vote": "N"
            },
            {
                "name": "Webber, Susan",
                "vote": "Y"
            },
            {
                "name": "Ellsworth, Jason",
                "vote": "N"
            },
            {
                "name": "Hinebauch, Steve",
                "vote": "N"
            },
            {
                "name": "O'Brien, Shannon",
                "vote": "Y"
            },
            {
                "name": "Welborn, Jeffrey",
                "vote": "Y"
            },
            {
                "name": "Emrich, Daniel",
                "vote": "Y"
            },
            {
                "name": "Kelker, Kathy",
                "vote": "Y"
            },
            {
                "name": "Olsen, Andrea",
                "vote": "Y"
            },
            {
                "name": "Zolnikov, Daniel",
                "vote": "Y"
            },
            {
                "name": "Esp, John",
                "vote": "N"
            },
            {
                "name": "Lang, Mike",
                "vote": "Y"
            },
            {
                "name": "Pope, Christopher",
                "vote": "Y"
            },
            {
                "name": "Fitzpatrick, Steve",
                "vote": "N"
            },
            {
                "name": "Lenz, Dennis",
                "vote": "N"
            },
            {
                "name": "Regier, Keith",
                "vote": "N"
            }
        ]
    }
]