{
    "key": "HB 23",
    "session": "20211",
    "billPageUrl": "http://laws.leg.mt.gov/legprd/LAW0210W$BSIV.ActionQuery?P_BILL_NO1=23&P_BLTP_BILL_TYP_CD=HB&Z_ACTION=Find&P_SESS=20211",
    "billTextUrl": "http://leg.mt.gov/bills/2021/billhtml/HB0023.htm",
    "billPdfUrl": "http://leg.mt.gov/bills/2021/billpdf/HB0023.pdf",
    "lc": "LC0374",
    "title": "Revise tax lien and tax deed process",
    "sponsor": "Becky Beard",
    "sponsorParty": "R",
    "sponsorDistrict": "HD 80",
    "statusDate": "02/23/2021",
    "lastAction": "Chapter Number Assigned",
    "billStatus": "Became Law",
    "fiscalNotesListUrl": null,
    "amendmentListUrl": "https://leg.mt.gov/laws/bills/20211/AmdPublicWeb/?bill=HB0023",
    "draftRequestor": null,
    "billRequestor": "Revenue Interim Committee",
    "primarySponsor": "Becky Beard",
    "subjects": [
        {
            "subject": "Local Government  (see also: City Subjects; County Subjects)",
            "fiscalCode": "",
            "voteReq": "Simple"
        },
        {
            "subject": "Taxation (Generally)",
            "fiscalCode": "",
            "voteReq": "Simple"
        },
        {
            "subject": "Taxation--Property",
            "fiscalCode": "",
            "voteReq": "Simple"
        }
    ],
    "voteRequirements": [
        "Simple"
    ],
    "deadlineCategory": "General Bills",
    "transmittalDeadline": "03/02/2021",
    "amendedReturnDeadline": "04/20/2021"
}